curators/__init__.py
curators/constants.py
curators/agents/__init__.py
curators/agents/contextual.py
curators/agents/naive.py
curators/agents/sequential.py
curators/applications/__init__.py
curators/applications/naive_email.py
curators/applications/naive_sms.py
curators/models/__init__.py
curators/models/model_base.py
curators/models/bandits/__init__.py
curators/models/bandits/bandit_base.py
curators/models/bandits/beta_bandit.py
curators/models/bandits/gaussian_bandit.py
curators/models/contextual_bandits/__init__.py
curators/models/contextual_bandits/cluster_bandit.py
curators-0.0.0b4.dist-info/LICENSE
curators-0.0.0b4.dist-info/METADATA
curators-0.0.0b4.dist-info/WHEEL
curators-0.0.0b4.dist-info/top_level.txt
curators-0.0.0b4.dist-info/RECORD
