Metadata-Version: 2.1
Name: curators
Version: 0.0.0b4
Summary: Models for decision optimization and automation
Home-page: https://github.com/BellwethrInc/curators
Author: Allen Grimm, Matt Moody, Jordan Roth
License: UNKNOWN
Keywords: sample,setuptools,development
Platform: UNKNOWN
Classifier: Development Status :: 4 - Beta
Classifier: Programming Language :: Python :: 3
Classifier: License :: OSI Approved :: Apache Software License
Classifier: Operating System :: OS Independent
Requires-Python: <4,>=3.6
License-File: LICENSE
Requires-Dist: numpy
Requires-Dist: scipy
